{"version":0,"notes":{"root":{"data":{"id":"root","title":"root","desc":"","updated":1605266684036,"created":1595961348801,"custom":{},"fname":"root","type":"note","vault":{"fsPath":".","selfContained":true,"name":"Dendron"},"contentHash":"2697051288b4bcc52d8c80c6d9445a89","links":[],"anchors":{},"children":[],"parent":null,"data":{}},"hash":"2697051288b4bcc52d8c80c6d9445a89"},"tutorial":{"data":{"id":"c1bs7wsjfbhb0zipaywqv1","title":"Tutorial","desc":"","updated":1658931733078,"created":1654223767390,"currentStep":0,"totalSteps":0,"custom":{"currentStep":0,"totalSteps":0},"fname":"tutorial","type":"note","vault":{"fsPath":".","selfContained":true,"name":"Dendron"},"contentHash":"ab12a0ebde45082967034f9eea2df3fc","links":[{"type":"wiki","from":{"fname":"tutorial","id":"c1bs7wsjfbhb0zipaywqv1","vaultName":"Dendron"},"value":"tutorial.one","position":{"start":{"line":61,"column":9,"offset":2424},"end":{"line":61,"column":25,"offset":2440},"indent":[]},"xvault":false,"sameFile":false,"to":{"fname":"tutorial.one"}},{"type":"wiki","from":{"fname":"tutorial","id":"c1bs7wsjfbhb0zipaywqv1","vaultName":"Dendron"},"value":"tutorial","position":{"start":{"line":65,"column":134,"offset":2762},"end":{"line":65,"column":146,"offset":2774},"indent":[]},"xvault":false,"sameFile":false,"to":{"fname":"tutorial"}}],"anchors":{"create-a-note":{"type":"header","text":"Create a Note","value":"create-a-note","line":14,"column":0,"depth":2},"find-a-note":{"type":"header","text":"Find a Note","value":"find-a-note","line":25,"column":0,"depth":2},"organize-your-notes":{"type":"header","text":"Organize your Notes","value":"organize-your-notes","line":36,"column":0,"depth":2},"create-a-link":{"type":"header","text":"Create a link","value":"create-a-link","line":47,"column":0,"depth":2},"navigate-a-link":{"type":"header","text":"Navigate a link","value":"navigate-a-link","line":59,"column":0,"depth":2},"refactor-a-note":{"type":"header","text":"Refactor a Note","value":"refactor-a-note","line":67,"column":0,"depth":2},"conclusion":{"type":"header","text":"Conclusion","value":"conclusion","line":76,"column":0,"depth":2},"next-steps":{"type":"header","text":"Next Steps","value":"next-steps","line":82,"column":0,"depth":2},"community":{"type":"header","text":"Community","value":"community","line":104,"column":0,"depth":2}},"children":[],"parent":null,"data":{}},"hash":"ab12a0ebde45082967034f9eea2df3fc"},"dend":{"data":{"id":"ow3yvsrmuf19acy26xko4i0","title":"Dend","desc":"","updated":1717491177055,"created":1717491164523,"custom":{},"fname":"dend","type":"note","vault":{"fsPath":".","selfContained":true,"name":"Dendron"},"contentHash":"e4a7a77af4fe6e4b8bf197aa49e3f213","links":[],"anchors":{},"children":[],"parent":null,"data":{}},"hash":"e4a7a77af4fe6e4b8bf197aa49e3f213"},"tutorial.two":{"data":{"id":"e00b3m0jccey7jfnsvr3oh1","title":"Two","desc":"","updated":1717491286763,"created":1717491218608,"custom":{},"fname":"tutorial.two","type":"note","vault":{"fsPath":".","selfContained":true,"name":"Dendron"},"contentHash":"19106509a3e5c1ef870c0b604a015505","links":[{"type":"wiki","from":{"fname":"tutorial.two","id":"e00b3m0jccey7jfnsvr3oh1","vaultName":"Dendron"},"value":"dend","position":{"start":{"line":2,"column":1,"offset":32},"end":{"line":2,"column":9,"offset":40},"indent":[]},"xvault":false,"sameFile":false,"to":{"fname":"dend"}}],"anchors":{},"children":[],"parent":null,"data":{}},"hash":"19106509a3e5c1ef870c0b604a015505"},"worknotes":{"data":{"id":"hje384f0o1mr53e0z6ngo5i","title":"Worknotes","desc":"","updated":1718293174339,"created":1717511047572,"custom":{},"fname":"worknotes","type":"note","vault":{"fsPath":".","selfContained":true,"name":"Dendron"},"contentHash":"a1131d51dfd433a586632728a083f433","links":[],"anchors":{},"children":[],"parent":null,"data":{}},"hash":"a1131d51dfd433a586632728a083f433"},"README":{"data":{"id":"t16sc4wrgaok8xm7q0stb2k","title":"README","desc":"","updated":1719156740355,"created":1719156740355,"custom":{},"fname":"README","type":"note","vault":{"fsPath":".","selfContained":true,"name":"Dendron"},"contentHash":"e8db396cb6299aab853e0b9feba657c5","links":[],"anchors":{"dendron-notes":{"type":"header","text":"dendron-notes","value":"dendron-notes","line":7,"column":0,"depth":1}},"children":[],"parent":null,"data":{}},"hash":"e8db396cb6299aab853e0b9feba657c5"},"templates.meet":{"data":{"id":"3z1yk988hg0qn1seca1eri8","title":"Meeting Notes Template","desc":"","updated":1718032660370,"created":1718032660370,"custom":{},"fname":"templates.meet","type":"note","vault":{"fsPath":".","selfContained":true,"name":"Dendron"},"contentHash":"7c708393a5bd300416157e1594d63db2","links":[{"type":"wiki","from":{"fname":"templates.meet","id":"3z1yk988hg0qn1seca1eri8","vaultName":"Dendron"},"value":"templates.meet","position":{"start":{"line":1,"column":11,"offset":10},"end":{"line":1,"column":29,"offset":28},"indent":[]},"xvault":false,"sameFile":false,"to":{"fname":"templates.meet"}},{"type":"wiki","from":{"fname":"templates.meet","id":"3z1yk988hg0qn1seca1eri8","vaultName":"Dendron"},"value":"user.john-doe","alias":"@john-doe","position":{"start":{"line":7,"column":3,"offset":248},"end":{"line":7,"column":12,"offset":257},"indent":[]},"xvault":false,"to":{"fname":"user.john-doe"}}],"anchors":{"attendees":{"type":"header","text":"Attendees","value":"attendees","line":9,"column":0,"depth":2},"goals":{"type":"header","text":"Goals","value":"goals","line":15,"column":0,"depth":2},"agenda":{"type":"header","text":"Agenda","value":"agenda","line":19,"column":0,"depth":2},"minutes":{"type":"header","text":"Minutes","value":"minutes","line":23,"column":0,"depth":2},"action-items":{"type":"header","text":"Action Items","value":"action-items","line":27,"column":0,"depth":2}},"children":[],"parent":null,"data":{}},"hash":"7c708393a5bd300416157e1594d63db2"},"meet.2024.06.10":{"data":{"id":"mgbq8stkm06d86b6m9scndb","title":"10","desc":"","updated":1718032660399,"created":1718032660399,"traitIds":["meetingNote"],"custom":{},"fname":"meet.2024.06.10","type":"note","vault":{"fsPath":".","selfContained":true,"name":"Dendron"},"contentHash":"b229a1e56cb46ab6c25861f4c8f02614","links":[{"type":"wiki","from":{"fname":"meet.2024.06.10","id":"mgbq8stkm06d86b6m9scndb","vaultName":"Dendron"},"value":"templates.meet","position":{"start":{"line":1,"column":11,"offset":10},"end":{"line":1,"column":29,"offset":28},"indent":[]},"xvault":false,"sameFile":false,"to":{"fname":"templates.meet"}},{"type":"wiki","from":{"fname":"meet.2024.06.10","id":"mgbq8stkm06d86b6m9scndb","vaultName":"Dendron"},"value":"user.john-doe","alias":"@john-doe","position":{"start":{"line":7,"column":3,"offset":248},"end":{"line":7,"column":12,"offset":257},"indent":[]},"xvault":false,"to":{"fname":"user.john-doe"}}],"anchors":{"attendees":{"type":"header","text":"Attendees","value":"attendees","line":11,"column":0,"depth":2},"goals":{"type":"header","text":"Goals","value":"goals","line":17,"column":0,"depth":2},"agenda":{"type":"header","text":"Agenda","value":"agenda","line":21,"column":0,"depth":2},"minutes":{"type":"header","text":"Minutes","value":"minutes","line":25,"column":0,"depth":2},"action-items":{"type":"header","text":"Action Items","value":"action-items","line":29,"column":0,"depth":2}},"children":[],"parent":null,"data":{}},"hash":"b229a1e56cb46ab6c25861f4c8f02614"}}}
